{ 
  "users": [
    {
    "id": 1,
    "name": "Leanne Graham",
    "username": "Bret",
    "email": "Sincere@april.biz",
    "avatar": "https://via.placeholder.com/150/771796"
  },
  {
    "id": 2,
    "name": "Ervin Howell",
    "username": "Antonette",
    "email": "Shanna@melissa.tv",
    "website": "anastasia.net",
    "avatar": "https://via.placeholder.com/150/24f355"
  },
  {
    "id": 3,
    "name": "Clementine Bauch",
    "username": "Samantha",
    "email": "Nathan@yesenia.net",
    "website": "ramiro.info",
    "avatar": "https://via.placeholder.com/150/d32776"
  },
  {
    "id": 4,
    "name": "Patricia Lebsack",
    "username": "Karianne",
    "email": "Julianne.OConner@kory.org",
    "website": "kale.biz",
    "avatar": "https://via.placeholder.com/150/f66b97"
  },
  {
    "id": 5,
    "name": "Chelsey Dietrich",
    "username": "Kamren",
    "email": "Lucio_Hettinger@annie.ca",
    "website": "demarco.info",
    "avatar": "https://via.placeholder.com/150/56a8c2"
  },
  {
    "id": 6,
    "name": "Mrs. Dennis Schulist",
    "username": "Leopoldo_Corkery",
    "email": "Karley_Dach@jasper.info",
    "website": "ola.org",
    "avatar": "https://via.placeholder.com/150/b0f7cc"
  },
  {
    "id": 7,
    "name": "Kurtis Weissnat",
    "username": "Elwyn.Skiles",
    "email": "Telly.Hoeger@billy.biz",
    "website": "elvis.io",
    "avatar": "https://via.placeholder.com/150/54176f"
  },
  {
    "id": 8,
    "name": "Nicholas Runolfsdottir V",
    "username": "Maxime_Nienow",
    "email": "Sherwood@rosamond.me",
    "website": "jacynthe.com",
    "avatar": "https://via.placeholder.com/150/51aa97"
  },
  {
    "id": 9,
    "name": "Glenna Reichert",
    "username": "Delphine",
    "email": "Chaim_McDermott@dana.io",
    "website": "conrad.com",
    "avatar": "https://via.placeholder.com/150/66b7d2"
  },
  {
    "id": 10,
    "name": "Clementina DuBuque",
    "username": "Moriah.Stanton",
    "email": "Rey.Padberg@karina.biz",
    "website": "ambrose.net",
    "avatar": "https://via.placeholder.com/150/197d29"
  }
  ]
 
}
